squarelet/__init__.py
squarelet/exceptions.py
squarelet/squarelet.py
squarelet/tests.py
python_squarelet-0.2.1.dist-info/METADATA
python_squarelet-0.2.1.dist-info/WHEEL
python_squarelet-0.2.1.dist-info/licenses/LICENSE
python_squarelet-0.2.1.dist-info/RECORD
