Metadata-Version: 2.4
Name: python-squarelet
Version: 0.2.1
Summary: Python library that handles token authentication for MuckRock and DocumentCloud
Project-URL: Homepage, https://github.com/MuckRock/python-squarelet
Project-URL: Bug Tracker, https://github.com/MuckRock/python-squarelet/issues
Author-email: duckduckgrayduck <sanjin@muckrock.com>
License-File: LICENSE
Classifier: License :: OSI Approved :: MIT License
Classifier: Operating System :: OS Independent
Classifier: Programming Language :: Python :: 3
Requires-Python: <=3.12,>=3.8
Requires-Dist: ratelimit
Requires-Dist: requests
Requires-Dist: urllib3
